bet365/README.MD
bet365/__init__.py
bet365/main.py
bet365/main_bak.py
bet365/plotly_history.py
bet365/quick_demo.py
bet365/renderer.py
bet365/test.py
bet365/csv/bet365_history.csv
bet365/csv/match_season_2020-2021.csv
bet365/csv/player_data.csv
bet365/csv/player_data_processed.csv
bet365/csv/team_season2020-2021_stats.csv
bet365/csv/team_stats_processed.csv
bet365/data_preprocessing/__init__.py
bet365/data_preprocessing/data_loader.py
bet365/data_preprocessing/player_data_preprocess.py
bet365/data_preprocessing/team_data_preprocess.py
bet365/data_preprocessing/unloader/__init__.py
bet365/data_preprocessing/unloader/unload_bet_history.py
bet365/data_preprocessing/unloader/unload_match_history.py
bet365/data_preprocessing/unloader/unload_player_data.py
bet365/data_preprocessing/unloader/unload_team_stats.py
bet365/player_stats/__init__.py
bet365/player_stats/explore_player.py
bet365/player_stats/plot_player.py
bet365/team_stats/__init__.py
bet365/team_stats/explore_team.py
crawler/__init__.py
crawler/main.py
crawler/scrapy.cfg
crawler/hls_downloader/__init__.py
crawler/hls_downloader/items.py
crawler/hls_downloader/middlewares.py
crawler/hls_downloader/pipelines.py
crawler/hls_downloader/settings.py
crawler/hls_downloader/spiders/__init__.py
crawler/hls_downloader/spiders/test-spider.py
crawler/hls_downloader/spiders/video_spider.py
crawler/hls_downloader/utils/__init__.py
crawler/hls_downloader/utils/ffmpeg
crawler/hls_downloader/utils/m3u8_parser.py
crawler/hls_downloader/utils/merge_ts.py
pylab/__init__.py
pylab/bet365/README.MD
pylab/bet365/__init__.py
pylab/bet365/main.py
pylab/bet365/main_bak.py
pylab/bet365/plotly_history.py
pylab/bet365/quick_demo.py
pylab/bet365/renderer.py
pylab/bet365/test.py
pylab/bet365/bin/google-sheet-util
pylab/bet365/csv/bet365_history.csv
pylab/bet365/csv/match_season_2020-2021.csv
pylab/bet365/csv/player_data.csv
pylab/bet365/csv/player_data_processed.csv
pylab/bet365/csv/team_season2020-2021_stats.csv
pylab_utils-0.5.dist-info/METADATA
pylab_utils-0.5.dist-info/WHEEL
pylab_utils-0.5.dist-info/entry_points.txt
pylab_utils-0.5.dist-info/top_level.txt
pylab_utils-0.5.dist-info/RECORD
